skyrc_ble/__init__.py
skyrc_ble/const.py
skyrc_ble/device.py
skyrc_ble/mc3000.py
skyrc_ble/models.py
skyrc_ble/py.typed
skyrc_ble-2.1.0.dist-info/LICENSE
skyrc_ble-2.1.0.dist-info/METADATA
skyrc_ble-2.1.0.dist-info/WHEEL
skyrc_ble-2.1.0.dist-info/RECORD
