Metadata-Version: 2.1
Name: skyrc-ble
Version: 2.1.0
Summary: Control SkyRC MC3000 battery chargers via BLE
Home-page: https://github.com/kroimon/skyrc-ble
License: MIT
Author: Stefan Rado
Author-email: github@kroimon.de
Requires-Python: >=3.9,<4.0
Classifier: Development Status :: 2 - Pre-Alpha
Classifier: Intended Audience :: Developers
Classifier: License :: OSI Approved :: MIT License
Classifier: Natural Language :: English
Classifier: Operating System :: OS Independent
Classifier: Programming Language :: Python :: 3
Classifier: Programming Language :: Python :: 3.9
Classifier: Programming Language :: Python :: 3.10
Classifier: Programming Language :: Python :: 3.11
Classifier: Programming Language :: Python :: 3.12
Classifier: Topic :: Software Development :: Libraries
Requires-Dist: bleak (>=0.19.0)
Requires-Dist: bleak-retry-connector (>=2.13.1)
Project-URL: Bug Tracker, https://github.com/kroimon/skyrc-ble/issues
Project-URL: Changelog, https://github.com/kroimon/skyrc-ble/blob/main/CHANGELOG.md
Project-URL: Documentation, https://skyrc-ble.readthedocs.io
Project-URL: Repository, https://github.com/kroimon/skyrc-ble
